{
  "model_name": "FluidCNN",
  "model_version": "1.0",
  "input_dim": 6712,
  "output_dim": 6712,
  "sequence_length": 3,
  "boundary_dims": 538,
  "equipment_dims": 6174,
  "hidden_channels": 512,
  "kernel_sizes": [3, 5, 7],
  "num_conv_layers": 4,
  "dilation_rates": [1, 2, 4, 8],
  "boundary_hidden_dim": 256,
  "equipment_hidden_dim": 512,
  "temporal_kernel_size": 3,
  "temporal_stride": 1,
  "temporal_padding": "same",
  "batch_norm": true,
  "use_residual": true,
  "activation": "relu",
  "projection_hidden_dim": 256,
  "learning_rate": 0.0001,
  "weight_decay": 1e-05,
  "dropout_rate": 0.1
}